fws_server
setup.cfg
setup.py
filtered_websocket/__init__.py
filtered_websocket/config_deserializer.py
filtered_websocket/server.py
filtered_websocket.egg-info/PKG-INFO
filtered_websocket.egg-info/SOURCES.txt
filtered_websocket.egg-info/dependency_links.txt
filtered_websocket.egg-info/requires.txt
filtered_websocket.egg-info/top_level.txt
filtered_websocket/filters/__init__.py
filtered_websocket/filters/base.py
filtered_websocket/filters/broadcast_messages.py
filtered_websocket/filters/broadcast_messages_by_token.py
filtered_websocket/filters/broadcast_pubsub.py
filtered_websocket/filters/stdout_messages.py
filtered_websocket/filters/stdout_pubsub.py
filtered_websocket/filters/stdout_rawdata.py
filtered_websocket/server_protocol/__init__.py
filtered_websocket/server_protocol/exception.py
filtered_websocket/server_protocol/frame.py
filtered_websocket/server_protocol/server.py
filtered_websocket/storage_objects/__init__.py
filtered_websocket/storage_objects/base.py
filtered_websocket/storage_objects/default.py
filtered_websocket/storage_objects/redis.py
filtered_websocket/storage_objects/subscribers/__init__.py
filtered_websocket/storage_objects/subscribers/base.py
filtered_websocket/storage_objects/subscribers/redis.py