Metadata-Version: 1.1
Name: filtered-websocket
Version: 0.4.1
Summary: A simple framework for constructing websocket servers from filter chains.
Home-page: https://github.com/mrrrgn/filtered_websocket/tarball/0.4.1
Author: Morgan Reece Phillips
Author-email: winter2718@gmail.com
License: BSD
Keywords: websocket TwistedWebsocket twisted
Platform: UNKNOWN
Classifier: Development Status :: 3 - Alpha
Classifier: Topic :: Utilities
Classifier: License :: OSI Approved :: BSD License
